{
  "Beijing": {
    "name": "Beijing",
    "alt_name": "Peking",
    "pinyin": "B\u011bij\u012bng",
    "hanzi": "\u5317\u4eac",
    "latitude": "39.9385466",
    "longitude": "116.1172766",
    "baidu": "",
    "glottolog": "beij1234",
    "iso": "cmn",
    "family": "Sinitic",
    "subgroup": "Mandarin",
    "subgroup_chinese": "\u7ba1\u8bdd",
    "subgroup_pinyin": "Gu\u0101nhu\u00e0",
    "classification_kurpaska": "Guanhua, Beijng",
    "note": ""
  },
  "Jinan": {
    "name": "Jinan",
    "alt_name": "",
    "pinyin": "J\u01d0n\u00e1n",
    "hanzi": "\u6d4e\u5357",
    "latitude": "36.690777",
    "longitude": "116.997299",
    "baidu": "",
    "glottolog": "jina1245",
    "iso": "cmn",
    "family": "Sinitic",
    "subgroup": "Mandarin",
    "subgroup_chinese": "\u7ba1\u8bdd",
    "subgroup_pinyin": "Gu\u0101nhu\u00e0",
    "classification_kurpaska": "Guanhua, Jilu",
    "note": ""
  },
  "Xi_an": {
    "name": "Xi_an",
    "alt_name": "Xi'an, Xi\u2019an",
    "pinyin": "X\u012b\u2019\u0101n",
    "hanzi": "\u897f\u5b89",
    "latitude": "34.228154",
    "longitude": "108.960571",
    "baidu": "",
    "glottolog": "xian1253",
    "iso": "cmn",
    "family": "Sinitic",
    "subgroup": "Mandarin",
    "subgroup_chinese": "\u7ba1\u8bdd",
    "subgroup_pinyin": "Gu\u0101nhu\u00e0",
    "classification_kurpaska": "Guanhua, Central Plain",
    "note": ""
  },
  "Taiyuan": {
    "name": "Taiyuan",
    "alt_name": "",
    "pinyin": "T\u00e0iyu\u00e1n",
    "hanzi": "\u592a\u539f",
    "latitude": "37.8632119",
    "longitude": "112.4024883",
    "baidu": "",
    "glottolog": "taiy1243",
    "iso": "cjy",
    "family": "Sinitic",
    "subgroup": "Jin",
    "subgroup_chinese": "\u664b",
    "subgroup_pinyin": "J\u00ecn",
    "classification_kurpaska": "Jin",
    "note": ""
  },
  "Wuhan": {
    "name": "Wuhan",
    "alt_name": "",
    "pinyin": "W\u01d4h\u00e0n",
    "hanzi": "\u6b66\u6c49",
    "latitude": "30.624086",
    "longitude": "114.305649",
    "baidu": "",
    "glottolog": "wuha1234",
    "iso": "cmn",
    "family": "Sinitic",
    "subgroup": "Mandarin",
    "subgroup_chinese": "\u7ba1\u8bdd",
    "subgroup_pinyin": "Gu\u0101nhu\u00e0",
    "classification_kurpaska": "Guanhua, Southwestern",
    "note": ""
  },
  "Chengdu": {
    "name": "Chengdu",
    "alt_name": "",
    "pinyin": "Ch\u00e9ngd\u016b",
    "hanzi": "\u6210\u90fd",
    "latitude": "30.605768",
    "longitude": "103.970947",
    "baidu": "",
    "glottolog": "chen1267",
    "iso": "cmn",
    "family": "Sinitic",
    "subgroup": "Mandarin",
    "subgroup_chinese": "\u7ba1\u8bdd",
    "subgroup_pinyin": "Gu\u0101nhu\u00e0",
    "classification_kurpaska": "Guanhua, Southwestern",
    "note": ""
  },
  "Hefei": {
    "name": "Hefei",
    "alt_name": "",
    "pinyin": "H\u00e9f\u00e9i",
    "hanzi": "\u5408\u80a5",
    "latitude": "31.873593",
    "longitude": "117.223663",
    "baidu": "",
    "glottolog": "hefe1234",
    "iso": "cmn",
    "family": "Sinitic",
    "subgroup": "Mandarin",
    "subgroup_chinese": "\u7ba1\u8bdd",
    "subgroup_pinyin": "Gu\u0101nhu\u00e0",
    "classification_kurpaska": "Guanhua, Jianghuai",
    "note": ""
  },
  "Yangzhou": {
    "name": "Yangzhou",
    "alt_name": "Yangchow",
    "pinyin": "Y\u00e1ngzh\u014du",
    "hanzi": "\u63da\u5dde",
    "latitude": "32.4171449",
    "longitude": "119.209227",
    "baidu": "",
    "glottolog": "yang1306",
    "iso": "cmn",
    "family": "Sinitic",
    "subgroup": "Mandarin",
    "subgroup_chinese": "\u7ba1\u8bdd",
    "subgroup_pinyin": "Gu\u0101nhu\u00e0",
    "classification_kurpaska": "",
    "note": ""
  },
  "Suzhou": {
    "name": "Suzhou",
    "alt_name": "",
    "pinyin": "S\u016bzh\u014du",
    "hanzi": "\u82cf\u5dde",
    "latitude": "31.3280439",
    "longitude": "120.364116",
    "baidu": "",
    "glottolog": "suzh1234",
    "iso": "wuu",
    "family": "Sinitic",
    "subgroup": "Wu",
    "subgroup_chinese": "\u5434",
    "subgroup_pinyin": "W\u00fa",
    "classification_kurpaska": "Wu, Taihu",
    "note": ""
  },
  "Wenzhou": {
    "name": "Wenzhou",
    "alt_name": "",
    "pinyin": "W\u0113nzh\u014du",
    "hanzi": "\u6e29\u5dde",
    "latitude": "28.005496",
    "longitude": "120.701179",
    "baidu": "",
    "glottolog": "ouji1238",
    "iso": "(wuu)",
    "family": "Sinitic",
    "subgroup": "Wu",
    "subgroup_chinese": "\u5434",
    "subgroup_pinyin": "W\u00fa",
    "classification_kurpaska": "Wu, Oujiang",
    "note": ""
  },
  "Changsha": {
    "name": "Changsha",
    "alt_name": "",
    "pinyin": "Ch\u00e1ngsh\u0101",
    "hanzi": "\u957f\u6c99",
    "latitude": "28.85032",
    "longitude": "112.943344",
    "baidu": "",
    "glottolog": "chan1326",
    "iso": "hsn",
    "family": "Sinitic",
    "subgroup": "Xiang",
    "subgroup_chinese": "\u6e58",
    "subgroup_pinyin": "Xi\u0101ng",
    "classification_kurpaska": "Xiang",
    "note": ""
  },
  "Shuangfeng": {
    "name": "Shuangfeng",
    "alt_name": "",
    "pinyin": "Shu\u0101ngf\u0113ng",
    "hanzi": "\u53cc\u5cf0",
    "latitude": "27.4569781",
    "longitude": "111.916486",
    "baidu": "",
    "glottolog": "shua1258",
    "iso": "hsn",
    "family": "Sinitic",
    "subgroup": "Xiang",
    "subgroup_chinese": "\u6e58",
    "subgroup_pinyin": "Xi\u0101ng",
    "classification_kurpaska": "",
    "note": "Shuangfeng is a part of the city Loudi (a xian) in Hunan."
  },
  "Nanchang": {
    "name": "Nanchang",
    "alt_name": "",
    "pinyin": "N\u00e1nch\u0101ng",
    "hanzi": "\u5357\u660c",
    "latitude": "28.706609",
    "longitude": "115.857468",
    "baidu": "",
    "glottolog": "nanc1254",
    "iso": "gan",
    "family": "Sinitic",
    "subgroup": "Gan",
    "subgroup_chinese": "\u8d63",
    "subgroup_pinyin": "G\u00e0n",
    "classification_kurpaska": "Gan",
    "note": ""
  },
  "Meixian": {
    "name": "Meixian",
    "alt_name": "",
    "pinyin": "M\u00e9ixi\u00e0n",
    "hanzi": "\u6885\u53bf",
    "latitude": "24.3522958",
    "longitude": "115.8903375",
    "baidu": "",
    "glottolog": "yuet1238",
    "iso": "hak",
    "family": "Sinitic",
    "subgroup": "Hakka",
    "subgroup_chinese": "\u5ba2\u5bb6",
    "subgroup_pinyin": "K\u00e8ji\u0101",
    "classification_kurpaska": "Hakka",
    "note": ""
  },
  "Guangzhou": {
    "name": "Guangzhou",
    "alt_name": "",
    "pinyin": "Gu\u01cengzh\u014du",
    "hanzi": "\u5e7f\u5dde",
    "latitude": "23.1253503",
    "longitude": "112.9476548",
    "baidu": "",
    "glottolog": "guan1279",
    "iso": "yue",
    "family": "Sinitic",
    "subgroup": "Yue",
    "subgroup_chinese": "\u7ca4",
    "subgroup_pinyin": "Yu\u00e8",
    "classification_kurpaska": "Yue, Guangfu",
    "note": ""
  },
  "Yangjiang": {
    "name": "Yangjiang",
    "alt_name": "",
    "pinyin": "Y\u00e1ngji\u0101ng",
    "hanzi": "\u9633\u6c5f",
    "latitude": "21.7895612",
    "longitude": "111.966667",
    "baidu": "",
    "glottolog": "yang1307",
    "iso": "yue",
    "family": "Sinitic",
    "subgroup": "Yue",
    "subgroup_chinese": "\u7ca4",
    "subgroup_pinyin": "Yu\u00e8",
    "classification_kurpaska": "",
    "note": ""
  },
  "Xiamen": {
    "name": "Xiamen",
    "alt_name": "",
    "pinyin": "Xi\u00e0m\u00e9n",
    "hanzi": "\u53a6\u95e8",
    "latitude": "24.49421",
    "longitude": "118.08918",
    "baidu": "",
    "glottolog": "xiam1236",
    "iso": "nan",
    "family": "Sinitic",
    "subgroup": "Min",
    "subgroup_chinese": "\u95fd",
    "subgroup_pinyin": "M\u01d0n",
    "classification_kurpaska": "Min, Southern",
    "note": ""
  },
  "Chaozhou": {
    "name": "Chaozhou",
    "alt_name": "",
    "pinyin": "Ch\u00e1ozh\u014du",
    "hanzi": "\u6f6e\u5dde",
    "latitude": "23.666667",
    "longitude": "116.633333",
    "baidu": "",
    "glottolog": "chao1238",
    "iso": "nan",
    "family": "Sinitic",
    "subgroup": "Min",
    "subgroup_chinese": "\u95fd",
    "subgroup_pinyin": "M\u01d0n",
    "classification_kurpaska": "",
    "note": ""
  },
  "Fuzhou": {
    "name": "Fuzhou",
    "alt_name": "Foochow",
    "pinyin": "F\u00fazh\u014du",
    "hanzi": "\u798f\u5dde",
    "latitude": "26.08904",
    "longitude": "119.294243",
    "baidu": "",
    "glottolog": "fuzh1239",
    "iso": "cdo",
    "family": "Sinitic",
    "subgroup": "Min",
    "subgroup_chinese": "\u95fd",
    "subgroup_pinyin": "M\u01d0n",
    "classification_kurpaska": "\u95fd",
    "note": ""
  },
  "Jian_ou": {
    "name": "Jian_ou",
    "alt_name": "Jian'ou, Jian\u2019ou",
    "pinyin": "Ji\u00e0n\u2019\u014du",
    "hanzi": "\u5efa\u74ef",
    "latitude": "27.04237",
    "longitude": "118.307419",
    "baidu": "",
    "glottolog": "jian1240",
    "iso": "mnp",
    "family": "Sinitic",
    "subgroup": "Min",
    "subgroup_chinese": "\u95fd",
    "subgroup_pinyin": "M\u01d0n",
    "classification_kurpaska": "Min, Northern",
    "note": ""
  },
  "Shenyang": {
    "name": "Shenyang",
    "alt_name": "",
    "pinyin": "Sh\u011bny\u00e1ng",
    "hanzi": "\u6c88\u9633",
    "latitude": "41.8049906",
    "longitude": "123.1563167",
    "baidu": "",
    "glottolog": "shen1252",
    "iso": "cmn",
    "family": "Sinitic",
    "subgroup": "Mandarin",
    "subgroup_chinese": "\u7ba1\u8bdd",
    "subgroup_pinyin": "Gu\u0101nhu\u00e0",
    "classification_kurpaska": "",
    "note": ""
  },
  "Kunming": {
    "name": "Kunming",
    "alt_name": "",
    "pinyin": "K\u016bnm\u00edng",
    "hanzi": "\u6606\u660e",
    "latitude": "25.049711",
    "longitude": "102.72274",
    "baidu": "",
    "glottolog": "kunm1234",
    "iso": "cmn",
    "family": "Sinitic",
    "subgroup": "Mandarin",
    "subgroup_chinese": "\u7ba1\u8bdd",
    "subgroup_pinyin": "Gu\u0101nhu\u00e0",
    "classification_kurpaska": "Guanhua, Southwestern",
    "note": ""
  },
  "Shanghai": {
    "name": "Shanghai",
    "alt_name": "",
    "pinyin": "Sh\u00e0ngh\u01cei",
    "hanzi": "\u4e0a\u6d77",
    "latitude": "31.222902",
    "longitude": "121.475372",
    "baidu": "",
    "glottolog": "shan1293",
    "iso": "wuu",
    "family": "Sinitic",
    "subgroup": "Wu",
    "subgroup_chinese": "\u5434",
    "subgroup_pinyin": "W\u00fa",
    "classification_kurpaska": "Wu, Taihu",
    "note": ""
  },
  "Hangzhou": {
    "name": "Hangzhou",
    "alt_name": "",
    "pinyin": "H\u00e1ngzh\u014du",
    "hanzi": "\u676d\u5dde",
    "latitude": "30.261316",
    "longitude": "120.0318057",
    "baidu": "",
    "glottolog": "hang1257",
    "iso": "(wuu)",
    "family": "Sinitic",
    "subgroup": "Wu",
    "subgroup_chinese": "\u5434",
    "subgroup_pinyin": "W\u00fa",
    "classification_kurpaska": "Wu, Taihu",
    "note": ""
  },
  "Nanning": {
    "name": "Nanning",
    "alt_name": "",
    "pinyin": "N\u00e1nn\u00edng",
    "hanzi": "\u5357\u5b81",
    "latitude": "22.848716",
    "longitude": "108.366165",
    "baidu": "",
    "glottolog": "nann1239",
    "iso": "(wuu)",
    "family": "Sinitic",
    "subgroup": "Pinghua",
    "subgroup_chinese": "\u5e73\u8bdd",
    "subgroup_pinyin": "P\u00ednghu\u00e0",
    "classification_kurpaska": "Pinghua",
    "note": ""
  },
  "Xianggang": {
    "name": "Xianggang",
    "alt_name": "Hong Kong",
    "pinyin": "Xi\u0101ngg\u01ceng",
    "hanzi": "\u9999\u6e2f",
    "latitude": "22.422645",
    "longitude": "114.098396",
    "baidu": "",
    "glottolog": "xian1255",
    "iso": "yue",
    "family": "Sinitic",
    "subgroup": "Yue",
    "subgroup_chinese": "\u7ca4",
    "subgroup_pinyin": "Yu\u00e8",
    "classification_kurpaska": "Yue",
    "note": ""
  },
  "Shantou": {
    "name": "Shantou",
    "alt_name": "",
    "pinyin": "Sh\u00e0nt\u00f3u",
    "hanzi": "\u6c55\u5934",
    "latitude": "23.3372419",
    "longitude": "116.6068173",
    "baidu": "",
    "glottolog": "shan1244",
    "iso": "nan",
    "family": "Sinitic",
    "subgroup": "Min",
    "subgroup_chinese": "\u95fd",
    "subgroup_pinyin": "M\u01d0n",
    "classification_kurpaska": "Min, Southern",
    "note": ""
  },
  "Haikou": {
    "name": "Haikou",
    "alt_name": "",
    "pinyin": "H\u01ceik\u01d2u",
    "hanzi": "\u6d77\u53e3",
    "latitude": "20.043869",
    "longitude": "110.329399",
    "baidu": "",
    "glottolog": "hain1237",
    "iso": "nan",
    "family": "Sinitic",
    "subgroup": "Min",
    "subgroup_chinese": "\u95fd",
    "subgroup_pinyin": "M\u01d0n",
    "classification_kurpaska": "Min, Qiongwen",
    "note": ""
  },
  "Taibei": {
    "name": "Taibei",
    "alt_name": "",
    "pinyin": "T\u00e1ib\u011bi",
    "hanzi": "\u53f0\u5317",
    "latitude": "25.0853403",
    "longitude": "121.4231642",
    "baidu": "",
    "glottolog": "taib1242",
    "iso": "nan",
    "family": "Sinitic",
    "subgroup": "Min",
    "subgroup_chinese": "\u95fd",
    "subgroup_pinyin": "M\u01d0n",
    "classification_kurpaska": "Min, Southern",
    "note": ""
  },
  "Taoyuan": {
    "name": "Taoyuan",
    "alt_name": "",
    "pinyin": "T\u00e1oyu\u00e1n",
    "hanzi": "\u6843\u56ed",
    "latitude": "24.854549",
    "longitude": "120.9520006",
    "baidu": "",
    "glottolog": "taoy1234",
    "iso": "hak",
    "family": "Sinitic",
    "subgroup": "Hakka",
    "subgroup_chinese": "\u5ba2\u5bb6",
    "subgroup_pinyin": "K\u00e8ji\u0101",
    "classification_kurpaska": "Hakka",
    "note": ""
  },
  "Xiangtan": {
    "name": "Xiangtan",
    "alt_name": "",
    "pinyin": "Xi\u0101ngt\u00e1n",
    "hanzi": "\u6e58\u6f6d",
    "latitude": "27.8482649",
    "longitude": "112.7688127",
    "baidu": "",
    "glottolog": "xian1254",
    "iso": "hsn",
    "family": "Sinitic",
    "subgroup": "Xiang",
    "subgroup_chinese": "\u6e58",
    "subgroup_pinyin": "Xi\u0101ng",
    "classification_kurpaska": "Xiang",
    "note": ""
  },
  "Shexian": {
    "name": "Shexian",
    "alt_name": "",
    "pinyin": "Sh\u00e8xi\u00e0n",
    "hanzi": "\u6b59\u53bf",
    "latitude": "30.589829",
    "longitude": "118.428268",
    "baidu": "",
    "glottolog": "shex1234",
    "iso": "czh",
    "family": "Sinitic",
    "subgroup": "Hui",
    "subgroup_chinese": "\u5fbd",
    "subgroup_pinyin": "Hu\u012b",
    "classification_kurpaska": "Hui",
    "note": ""
  },
  "Tunxi": {
    "name": "Tunxi",
    "alt_name": "",
    "pinyin": "T\u016bnx\u012b",
    "hanzi": "\u5c6f\u6eaa",
    "latitude": "29.7201616",
    "longitude": "118.2294365",
    "baidu": "",
    "glottolog": "tunx1234",
    "iso": "czh",
    "family": "Sinitic",
    "subgroup": "Hui",
    "subgroup_chinese": "\u5fbd",
    "subgroup_pinyin": "Hu\u012b",
    "classification_kurpaska": "Hui",
    "note": ""
  },
  "Pingyao": {
    "name": "Pingyao",
    "alt_name": "",
    "pinyin": "P\u00edngy\u00e1o",
    "hanzi": "\u5e73\u9065",
    "latitude": "37.1390706",
    "longitude": "111.9656111",
    "baidu": "",
    "glottolog": "ping1247",
    "iso": "cjy",
    "family": "Sinitic",
    "subgroup": "Jin",
    "subgroup_chinese": "\u664b",
    "subgroup_pinyin": "J\u00ecn",
    "classification_kurpaska": "Jin",
    "note": ""
  },
  "Huhehaote": {
    "name": "Huhehaote",
    "alt_name": "",
    "pinyin": "H\u016bh\u00e8h\u00e0ot\u00e8",
    "hanzi": "\u547c\u548c\u6d69\u7279",
    "latitude": "40.855526",
    "longitude": "111.743889",
    "baidu": "",
    "glottolog": "huhe1234",
    "iso": "cjy",
    "family": "Sinitic",
    "subgroup": "Jin",
    "subgroup_chinese": "\u664b",
    "subgroup_pinyin": "J\u00ecn",
    "classification_kurpaska": "Jin",
    "note": ""
  },
  "Tianjin": {
    "name": "Tianjin",
    "alt_name": "",
    "pinyin": "Ti\u0101nj\u012bn",
    "hanzi": "\u5929\u6d25",
    "latitude": "39.186072",
    "longitude": "117.215424",
    "baidu": "",
    "glottolog": "tian1238",
    "iso": "cmn",
    "family": "Sinitic",
    "subgroup": "Mandarin",
    "subgroup_chinese": "\u7ba1\u8bdd",
    "subgroup_pinyin": "Gu\u0101nhu\u00e0",
    "classification_kurpaska": "Guanhua, Jilu",
    "note": ""
  },
  "Qingdao": {
    "name": "Qingdao",
    "alt_name": "Tsingtao",
    "pinyin": "Q\u012bngd\u01ceo",
    "hanzi": "\u9752\u5c9b",
    "latitude": "36.089393",
    "longitude": "120.379715",
    "baidu": "",
    "glottolog": "qing1240",
    "iso": "cmn",
    "family": "Sinitic",
    "subgroup": "Mandarin",
    "subgroup_chinese": "\u7ba1\u8bdd",
    "subgroup_pinyin": "Gu\u0101nhu\u00e0",
    "classification_kurpaska": "Guanhua, Jiaoliao",
    "note": ""
  },
  "Nanjing": {
    "name": "Nanjing",
    "alt_name": "",
    "pinyin": "N\u00e1nj\u012bng",
    "hanzi": "\u5357\u4eac",
    "latitude": "32.0989607",
    "longitude": "118.4575646",
    "baidu": "",
    "glottolog": "nanj1234",
    "iso": "cmn",
    "family": "Sinitic",
    "subgroup": "Mandarin",
    "subgroup_chinese": "\u7ba1\u8bdd",
    "subgroup_pinyin": "Gu\u0101nhu\u00e0",
    "classification_kurpaska": "Guanhua, Jianghuai",
    "note": ""
  },
  "Zhengzhou": {
    "name": "Zhengzhou",
    "alt_name": "",
    "pinyin": "Zh\u00e8ngzh\u014du",
    "hanzi": "\u90d1\u5dde",
    "latitude": "34.807715",
    "longitude": "113.639374",
    "baidu": "",
    "glottolog": "zhen1241",
    "iso": "cmn",
    "family": "Sinitic",
    "subgroup": "Mandarin",
    "subgroup_chinese": "\u7ba1\u8bdd",
    "subgroup_pinyin": "Gu\u0101nhu\u00e0",
    "classification_kurpaska": "Guanhua, Central Plain",
    "note": ""
  },
  "Guiyang": {
    "name": "Guiyang",
    "alt_name": "",
    "pinyin": "Gu\u00ecy\u00e1ng",
    "hanzi": "\u8d35\u9633",
    "latitude": "26.71691",
    "longitude": "106.638336",
    "baidu": "",
    "glottolog": "guiy1235",
    "iso": "cmn",
    "family": "Sinitic",
    "subgroup": "Mandarin",
    "subgroup_chinese": "\u7ba1\u8bdd",
    "subgroup_pinyin": "Gu\u0101nhu\u00e0",
    "classification_kurpaska": "Guanhua, Southwestern",
    "note": ""
  },
  "Ha_erbin": {
    "name": "Ha_erbin",
    "alt_name": "Harbin, Ha'erbin, Ha\u2019erbin",
    "pinyin": "H\u0101\u011brb\u012bn",
    "hanzi": "\u54c8\u5c14\u6ee8",
    "latitude": "45.846595",
    "longitude": "126.551056",
    "baidu": "",
    "glottolog": "haer1234",
    "iso": "cmn",
    "family": "Sinitic",
    "subgroup": "Mandarin",
    "subgroup_chinese": "\u7ba1\u8bdd",
    "subgroup_pinyin": "Gu\u0101nhu\u00e0",
    "classification_kurpaska": "Guanhua, Northeastern",
    "note": ""
  },
  "Yinchuan": {
    "name": "Yinchuan",
    "alt_name": "",
    "pinyin": "Y\u00ednchu\u0101n",
    "hanzi": "\u94f6\u5ddd",
    "latitude": "38.546662",
    "longitude": "106.240082",
    "baidu": "",
    "glottolog": "yinc1239",
    "iso": "cmn",
    "family": "Sinitic",
    "subgroup": "Mandarin",
    "subgroup_chinese": "\u7ba1\u8bdd",
    "subgroup_pinyin": "Gu\u0101nhu\u00e0",
    "classification_kurpaska": "Guanhua, Lanyin",
    "note": ""
  },
  "Lanzhou": {
    "name": "Lanzhou",
    "alt_name": "",
    "pinyin": "L\u00e1nzh\u014du",
    "hanzi": "\u5170\u5dde",
    "latitude": "36.080515",
    "longitude": "103.838425",
    "baidu": "",
    "glottolog": "lanz1234",
    "iso": "cmn",
    "family": "Sinitic",
    "subgroup": "Mandarin",
    "subgroup_chinese": "\u7ba1\u8bdd",
    "subgroup_pinyin": "Gu\u0101nhu\u00e0",
    "classification_kurpaska": "Guanhua, Lanyin",
    "note": ""
  },
  "Xining": {
    "name": "Xining",
    "alt_name": "",
    "pinyin": "X\u012bn\u00edng",
    "hanzi": "\u897f\u5b81",
    "latitude": "36.671283",
    "longitude": "101.776886",
    "baidu": "",
    "glottolog": "xini1234",
    "iso": "cmn",
    "family": "Sinitic",
    "subgroup": "Mandarin",
    "subgroup_chinese": "\u7ba1\u8bdd",
    "subgroup_pinyin": "Gu\u0101nhu\u00e0",
    "classification_kurpaska": "Guanhua, Central Plain",
    "note": ""
  },
  "Wulumuqi": {
    "name": "Wulumuqi",
    "alt_name": "\u00dcr\u00fcmqi",
    "pinyin": "W\u016bl\u01d4m\u00f9q\u00ed",
    "hanzi": "\u4e4c\u9c81\u6728\u9f50",
    "latitude": "43.8216271",
    "longitude": "87.4226688",
    "baidu": "",
    "glottolog": "wulu1243",
    "iso": "cmn",
    "family": "Sinitic",
    "subgroup": "Mandarin",
    "subgroup_chinese": "\u7ba1\u8bdd",
    "subgroup_pinyin": "Gu\u0101nhu\u00e0",
    "classification_kurpaska": "Guanhua, Lanyin",
    "note": ""
  },
  "Rongcheng": {
    "name": "Rongcheng",
    "alt_name": "",
    "pinyin": "R\u00f3ngch\u00e9ng",
    "hanzi": "\u8363\u6210",
    "latitude": "37.130642",
    "longitude": "122.434269",
    "baidu": "",
    "glottolog": "rong1271",
    "iso": "cmn",
    "family": "Sinitic",
    "subgroup": "Mandarin",
    "subgroup_chinese": "\u7ba1\u8bdd",
    "subgroup_pinyin": "Gu\u0101nhu\u00e0",
    "classification_kurpaska": "",
    "note": ""
  },
  "Jixi": {
    "name": "Jixi",
    "alt_name": "",
    "pinyin": "J\u00ecx\u012b",
    "hanzi": "\u7ee9\u6eaa",
    "latitude": "30.071111",
    "longitude": "118.592222",
    "baidu": "",
    "glottolog": "jixi1238",
    "iso": "czh",
    "family": "Sinitic",
    "subgroup": "Hui",
    "subgroup_chinese": "\u5fbd",
    "subgroup_pinyin": "Hu\u012b",
    "classification_kurpaska": "",
    "note": ""
  },
  "Loudi": {
    "name": "Loudi",
    "alt_name": "",
    "pinyin": "L\u00f3ud\u00ee",
    "hanzi": "\u5a04\u5e95",
    "latitude": "27.733333",
    "longitude": "111.9281883",
    "baidu": "",
    "glottolog": "loud1234",
    "iso": "hsn",
    "family": "Sinitic",
    "subgroup": "Xiang",
    "subgroup_chinese": "\u6e58",
    "subgroup_pinyin": "Xi\u0101ng",
    "classification_kurpaska": "",
    "note": ""
  },
  "Guilin": {
    "name": "Guilin",
    "alt_name": "",
    "pinyin": "Gu\u012bl\u00edn",
    "hanzi": "\u6842\u6797",
    "latitude": "25.266667",
    "longitude": "110.283333",
    "baidu": "",
    "glottolog": "guil1241",
    "iso": "(wuu)",
    "family": "Sinitic",
    "subgroup": "Pinghua",
    "subgroup_chinese": "\u5e73\u8bdd",
    "subgroup_pinyin": "P\u00ednghu\u00e0",
    "classification_kurpaska": "",
    "note": ""
  },
  "Yingshan": {
    "name": "Yingshan",
    "alt_name": "",
    "pinyin": "Y\u012bngsh\u0101n",
    "hanzi": "\u82f1\u5c71",
    "latitude": "30.7462984",
    "longitude": "115.3468074",
    "baidu": "",
    "glottolog": "ying1249",
    "iso": "cmn",
    "family": "Sinitic",
    "subgroup": "Mandarin",
    "subgroup_chinese": "\u7ba1\u8bdd",
    "subgroup_pinyin": "Gu\u0101nhu\u00e0",
    "classification_kurpaska": "",
    "note": "It is not clear which Yingshan is meant, as there are many districts which could qualify as the name. Juding from the fact that Yingshan clusters closely with Wuhan, it is likely that it is \u82f1\u5c71, east of W\u01d4h\u00e0n."
  },
  "Anyi": {
    "name": "Anyi",
    "alt_name": "",
    "pinyin": "\u0100ny\u00ec",
    "hanzi": "\u5b89\u7fa9",
    "latitude": "28.84359",
    "longitude": "115.54773",
    "baidu": "",
    "glottolog": "anyi1247",
    "iso": "gan",
    "family": "Sinitic",
    "subgroup": "Gan",
    "subgroup_chinese": "\u8d63",
    "subgroup_pinyin": "G\u00e0n",
    "classification_kurpaska": "",
    "note": "Anyi is a city in the county of Nanchang."
  },
  "Liancheng": {
    "name": "Liancheng",
    "alt_name": "",
    "pinyin": "L\u00edanch\u00e9ng",
    "hanzi": "\u8fde\u57ce",
    "latitude": "25.566667",
    "longitude": "116.783333",
    "baidu": "",
    "glottolog": "lian1259",
    "iso": "hak",
    "family": "Sinitic",
    "subgroup": "Hakka",
    "subgroup_chinese": "\u5ba2\u5bb6",
    "subgroup_pinyin": "K\u00e8ji\u0101",
    "classification_kurpaska": "",
    "note": ""
  },
  "Hankou": {
    "name": "Hankou",
    "alt_name": "",
    "pinyin": "H\u00e0nk\u01d2u",
    "hanzi": "\u6c49\u53e3",
    "latitude": "30.581179",
    "longitude": "114.272597",
    "baidu": "",
    "glottolog": "hank1234",
    "iso": "cmn",
    "family": "Sinitic",
    "subgroup": "Mandarin",
    "subgroup_chinese": "\u7ba1\u8bdd",
    "subgroup_pinyin": "Gu\u0101nhu\u00e0",
    "classification_kurpaska": "",
    "note": "Hankou remains a commonly used name for the part of Wuhan urban area north of the Yangtze and Han Rivers. [W] Hankou is the old name for a city that is now part of Wuhan."
  },
  "Ningxia": {
    "name": "Ningxia",
    "alt_name": "",
    "pinyin": "N\u00edngxi\u00e0",
    "hanzi": "\u5b81\u590f",
    "latitude": "38.546662",
    "longitude": "106.240082",
    "baidu": "",
    "glottolog": "ning1279",
    "iso": "cmn",
    "family": "Sinitic",
    "subgroup": "Mandarin",
    "subgroup_chinese": "\u7ba1\u8bdd",
    "subgroup_pinyin": "Gu\u0101nhu\u00e0",
    "classification_kurpaska": "",
    "note": "Ningxia is a region in China, containing the city Yinchuan."
  },
  "Yuci": {
    "name": "Yuci",
    "alt_name": "",
    "pinyin": "Y\u00fac\u00ec",
    "hanzi": "\u6986\u6b21",
    "latitude": "37.6394177",
    "longitude": "112.5650222",
    "baidu": "",
    "glottolog": "yuci1234",
    "iso": "cmn",
    "family": "Sinitic",
    "subgroup": "Mandarin",
    "subgroup_chinese": "\u7ba1\u8bdd",
    "subgroup_pinyin": "Gu\u0101nhu\u00e0",
    "classification_kurpaska": "",
    "note": "In the map shown in Hamed2006, Yuci is placed close to Yingshan. however, comparing this with other maps, there is no place that could be identified with the name Yuci. I assume that, given that Yuci clusters as Northern dialect, it is much higher up in the North."
  },
  "Zhangping": {
    "name": "Zhangping",
    "alt_name": "",
    "pinyin": "Zh\u0101ngp\u00edng",
    "hanzi": "\u6f33\u5e73",
    "latitude": "25.283333",
    "longitude": "117.416667",
    "baidu": "",
    "glottolog": "zhan1240",
    "iso": "nan",
    "family": "Sinitic",
    "subgroup": "Min",
    "subgroup_chinese": "\u95fd",
    "subgroup_pinyin": "M\u01d0n",
    "classification_kurpaska": "",
    "note": ""
  },
  "Ningbo": {
    "name": "Ningbo",
    "alt_name": "",
    "pinyin": "N\u00edngb\u014d",
    "hanzi": "\u5b81\u6ce2",
    "latitude": "29.866667",
    "longitude": "121.533333",
    "baidu": "",
    "glottolog": "ning1280",
    "iso": "(wuu)",
    "family": "Sinitic",
    "subgroup": "Wu",
    "subgroup_chinese": "\u5434",
    "subgroup_pinyin": "W\u00fa",
    "classification_kurpaska": "",
    "note": ""
  },
  "Shanghai_B": {
    "name": "Shanghai_B",
    "alt_name": "",
    "pinyin": "Sh\u00e0ngh\u01cei",
    "hanzi": "\u4e0a\u6d77",
    "latitude": "31.222902",
    "longitude": "121.475372",
    "baidu": "",
    "glottolog": "shan1293",
    "iso": "(wuu)",
    "family": "Sinitic",
    "subgroup": "Wu",
    "subgroup_chinese": "\u5434",
    "subgroup_pinyin": "W\u00fa",
    "classification_kurpaska": "Wu, Taihu",
    "note": ""
  },
  "Heping": {
    "name": "Heping",
    "alt_name": "",
    "pinyin": "H\u00e9p\u00edng",
    "hanzi": "\u548c\u5e73",
    "latitude": "27.112778",
    "longitude": "117.297222",
    "baidu": "",
    "glottolog": "shao1235",
    "iso": "mnp",
    "family": "Sinitic",
    "subgroup": "Min",
    "subgroup_chinese": "\u95fd",
    "subgroup_pinyin": "M\u01d0n",
    "classification_kurpaska": "",
    "note": ""
  },
  "Zhenqian": {
    "name": "Zhenqian",
    "alt_name": "",
    "pinyin": "Zh\u00e8nqi\u00e1n",
    "hanzi": "\u93ae\u524d",
    "latitude": "25.2474987",
    "longitude": "119.2778522",
    "baidu": "",
    "glottolog": "zhen1242",
    "iso": "mnp",
    "family": "Sinitic",
    "subgroup": "Min",
    "subgroup_chinese": "\u95fd",
    "subgroup_pinyin": "M\u01d0n",
    "classification_kurpaska": "",
    "note": ""
  },
  "Jiangshan": {
    "name": "Jiangshan",
    "alt_name": "",
    "pinyin": "Ji\u0101ngsh\u0101n",
    "hanzi": "\u6c5f\u5c71",
    "latitude": "28.5629681",
    "longitude": "118.3206425",
    "baidu": "http://baike.baidu.com/view/763966.htm",
    "glottolog": "long1386",
    "iso": "wuu",
    "family": "Sinitic",
    "subgroup": "Wu",
    "subgroup_chinese": "\u5434",
    "subgroup_pinyin": "W\u00fa",
    "classification_kurpaska": "",
    "note": ""
  },
  "Jiangyong": {
    "name": "Jiangyong",
    "alt_name": "",
    "pinyin": "Ji\u0101ngy\u01d2ng",
    "hanzi": "",
    "latitude": "",
    "longitude": "",
    "baidu": "",
    "glottolog": "jian1243",
    "iso": "hsn",
    "family": "Sinitic",
    "subgroup": "Xiang",
    "subgroup_chinese": "\u6e58",
    "subgroup_pinyin": "Xi\u0101ng",
    "classification_kurpaska": "",
    "note": ""
  },
  "Old_Chinese": {
    "name": "Old_Chinese",
    "alt_name": "",
    "pinyin": "Sh\u00e0ngg\u01d4 H\u00e0ny\u01d4",
    "hanzi": "\u4e0a\u53e4\u6c49\u8bed",
    "latitude": "",
    "longitude": "",
    "baidu": "",
    "glottolog": "shan1294",
    "iso": "",
    "family": "Sinitic",
    "subgroup": "Old_Chinese",
    "subgroup_chinese": "",
    "subgroup_pinyin": "",
    "classification_kurpaska": "",
    "note": ""
  },
  "Middle_Chinese": {
    "name": "Middle_Chinese",
    "alt_name": "",
    "pinyin": "Zh\u014dngg\u01d4 H\u00e0ny\u01d4",
    "hanzi": "\u4e2d\u53e4\u6c49\u8bed",
    "latitude": "",
    "longitude": "",
    "baidu": "",
    "glottolog": "zhon1237",
    "iso": "",
    "family": "Sinitic",
    "subgroup": "Middle_Chinese",
    "subgroup_chinese": "",
    "subgroup_pinyin": "",
    "classification_kurpaska": "",
    "note": ""
  },
  "Common_Chinese": {
    "name": "Common_Chinese",
    "alt_name": "",
    "pinyin": "",
    "hanzi": "",
    "latitude": "",
    "longitude": "",
    "baidu": "",
    "glottolog": "comm1247",
    "iso": "",
    "family": "Sinitic",
    "subgroup": "Middle_Chinese",
    "subgroup_chinese": "",
    "subgroup_pinyin": "",
    "classification_kurpaska": "",
    "note": ""
  },
  "Jianchuan": {
    "name": "Jianchuan",
    "alt_name": "Bai (Jianchuan), Jianchuan Bai",
    "pinyin": "Ji\u00e0nchu\u0101n",
    "hanzi": "\u5251\u5ddd",
    "latitude": "26.538056",
    "longitude": "99.910000",
    "baidu": "",
    "glottolog": "jian1239",
    "iso": "bca",
    "family": "Bai",
    "subgroup": "Central",
    "subgroup_chinese": "",
    "subgroup_pinyin": "",
    "classification_kurpaska": "",
    "note": ""
  },
  "Eryuan": {
    "name": "Eryuan",
    "alt_name": "",
    "pinyin": "\u011aryu\u00e1n",
    "hanzi": "\u6d31\u6e90",
    "latitude": "26.0991374",
    "longitude": "99.9416161",
    "baidu": "",
    "glottolog": "eryu1239",
    "iso": "bca",
    "family": "Bai",
    "subgroup": "Central",
    "subgroup_chinese": "",
    "subgroup_pinyin": "",
    "classification_kurpaska": "",
    "note": ""
  },
  "Heqing": {
    "name": "Heqing",
    "alt_name": "",
    "pinyin": "H\u00e8q\u00ecng",
    "hanzi": "\u9e64\u5e86",
    "latitude": "26.5536208",
    "longitude": "100.1396921",
    "baidu": "",
    "glottolog": "heqi1238",
    "iso": "bca",
    "family": "Bai",
    "subgroup": "Central",
    "subgroup_chinese": "",
    "subgroup_pinyin": "",
    "classification_kurpaska": "",
    "note": ""
  },
  "Lanping": {
    "name": "Lanping",
    "alt_name": "",
    "pinyin": "L\u00e1np\u00edng",
    "hanzi": "\u5170\u576a",
    "latitude": "26.5158555",
    "longitude": "99.2581092",
    "baidu": "",
    "glottolog": "lanp1241",
    "iso": "bca",
    "family": "Bai",
    "subgroup": "Central",
    "subgroup_chinese": "",
    "subgroup_pinyin": "",
    "classification_kurpaska": "",
    "note": ""
  },
  "Zhoucheng": {
    "name": "Zhoucheng",
    "alt_name": "",
    "pinyin": "Zh\u014duch\u00e9ng",
    "hanzi": "\u5468\u57ce",
    "latitude": "25.8958633",
    "longitude": "100.0987848",
    "baidu": "",
    "glottolog": "zhou1234",
    "iso": "bfs",
    "family": "Bai",
    "subgroup": "Southern",
    "subgroup_chinese": "",
    "subgroup_pinyin": "",
    "classification_kurpaska": "",
    "note": ""
  },
  "Qiliqiao": {
    "name": "Qiliqiao",
    "alt_name": "",
    "pinyin": "Q\u012bl\u01d0qi\u00e1o",
    "hanzi": "\u4e03\u91cc\u6865",
    "latitude": "25.6553283",
    "longitude": "100.1709288",
    "baidu": "",
    "glottolog": "qili1234",
    "iso": "bfs",
    "family": "Bai",
    "subgroup": "Southern",
    "subgroup_chinese": "",
    "subgroup_pinyin": "",
    "classification_kurpaska": "",
    "note": ""
  },
  "Yunlong": {
    "name": "Yunlong",
    "alt_name": "",
    "pinyin": "Y\u00fanl\u00f3ng",
    "hanzi": "\u4e91\u9f99",
    "latitude": "25.9223745",
    "longitude": "99.0352884",
    "baidu": "",
    "glottolog": "yunl1238",
    "iso": "bca",
    "family": "Bai",
    "subgroup": "Central",
    "subgroup_chinese": "",
    "subgroup_pinyin": "",
    "classification_kurpaska": "",
    "note": ""
  },
  "Xiangyun": {
    "name": "Xiangyun",
    "alt_name": "",
    "pinyin": "Xi\u00e1ngy\u00fan",
    "hanzi": "\u7965\u4e91",
    "latitude": "25.5313657",
    "longitude": "100.4478932",
    "baidu": "",
    "glottolog": "xian1250",
    "iso": "bfs",
    "family": "Bai",
    "subgroup": "Southern",
    "subgroup_chinese": "",
    "subgroup_pinyin": "",
    "classification_kurpaska": "",
    "note": ""
  },
  "Luobenzhuo": {
    "name": "Luobenzhuo",
    "alt_name": "",
    "pinyin": "L\u00f9b\u011bnzhu\u00f3",
    "hanzi": "\u6d1b\u672c\u5353",
    "latitude": "26.4240223",
    "longitude": "98.8862088",
    "baidu": "",
    "glottolog": "nuji1238",
    "iso": "bfc",
    "family": "Bai",
    "subgroup": "Northern",
    "subgroup_chinese": "",
    "subgroup_pinyin": "",
    "classification_kurpaska": "",
    "note": ""
  },
  "Late_Han_Chinese": {
    "name": "Late_Han_Chinese",
    "alt_name": "",
    "pinyin": "",
    "hanzi": "",
    "latitude": "",
    "longitude": "",
    "baidu": "",
    "glottolog": "late1251",
    "iso": "",
    "family": "Sinitic",
    "subgroup": "Old_Chinese",
    "subgroup_chinese": "",
    "subgroup_pinyin": "",
    "classification_kurpaska": "",
    "note": ""
  },
  "Dancun": {
    "name": "Dancun",
    "alt_name": "",
    "pinyin": "D\u00e0nc\u016bn",
    "hanzi": "\u6de1\u6751",
    "latitude": "22.2750324",
    "longitude": "112.7199202",
    "baidu": "",
    "glottolog": "danc1234",
    "iso": "yue",
    "family": "Sinitic",
    "subgroup": "Yue",
    "subgroup_chinese": "\u7ca4",
    "subgroup_pinyin": "Yu\u00e8",
    "classification_kurpaska": "Yue, Siyi",
    "note": "Yue-Hashimoto on Dancun: \u00abDancun is a small village lying in the central northern part of Taishan county and situated about thirty li west of Taicheng, while Baishui is within ten li west of it.\u00bb"
  },
  "Bijiang": {
    "name": "Bijiang",
    "alt_name": "Bai (Bijiang), Bijiang Bai",
    "pinyin": "",
    "hanzi": "",
    "latitude": "",
    "longitude": "",
    "baidu": "",
    "glottolog": "biji1251",
    "iso": "bfc",
    "family": "Bai",
    "subgroup": "Northern",
    "subgroup_chinese": "",
    "subgroup_pinyin": "",
    "classification_kurpaska": "",
    "note": ""
  },
  "Dali": {
    "name": "Dali",
    "alt_name": "Bai (Dali), Dali Bai",
    "pinyin": "",
    "hanzi": "",
    "latitude": "",
    "longitude": "",
    "baidu": "",
    "glottolog": "dali1242",
    "iso": "bfs",
    "family": "Bai",
    "subgroup": "Southern",
    "subgroup_chinese": "",
    "subgroup_pinyin": "",
    "classification_kurpaska": "",
    "note": ""
  }
}